{
  "context": {
    "domain": "beckn:dataset:ddm:1.0.0",
    "action": "on_discover",
    "version": "2.0.0",
    "bap_id": "ev-charging.sandbox1.com",
    "bap_uri": "https://ev-charging.sandbox1.com",
    "bpp_id": "ev-charging.sandbox2.com",
    "bpp_uri": "https://ev-charging.sandbox2.com",
    "transaction_id": "b2bb2763-8342-4c0b-a32a-2bc6a9dab8f2",
    "message_id": "02cce6cf-76c4-48e5-b5d0-fe430a1d8c34",
    "timestamp": "2025-02-15T10:00:01Z",
    "ttl": "PT30S"
  },
  "message": {
    "catalog": {
      "@context": "https://raw.githubusercontent.com/beckn/protocol-specifications-v2/core-v2.0.0-rc/schema/core/v2/context.jsonld",
      "@type": "beckn:Catalog",
      "beckn:id": "catalog-climate-rain-001",
      "beckn:descriptor": {
        "@type": "beckn:Descriptor",
        "schema:name": "ClimateData — Rainwater Probability Datasets",
        "beckn:shortDesc": "Historical and forecast rain probability datasets for Indian cities and regions"
      },
      "beckn:bppId": "climate-data.example.com",
      "beckn:bppUri": "https://climate-data.example.com/beckn",
      "beckn:items": [
        {
          "@context": "https://raw.githubusercontent.com/beckn/protocol-specifications-v2/core-v2.0.0-rc/schema/core/v2/context.jsonld",
          "@type": "beckn:Item",
          "beckn:id": "ds-rainprob-delhi-ncr-march-2025",
          "beckn:descriptor": {
            "@type": "beckn:Descriptor",
            "schema:name": "Rainwater Probability — Delhi NCR — March 2025",
            "beckn:shortDesc": "Daily probability of rainfall (%) for grid cells covering Delhi NCR for March 2025",
            "beckn:longDesc": "Static dataset providing daily precipitation probability (%) for each 5km x 5km grid cell covering the Delhi-NCR region for the period 2025-03-01 to 2025-03-31. Derived from IMD and model ensemble outputs, suitable for hydrology, agriculture, and urban drainage planning."
          },
          "beckn:category": {
            "@type": "schema:CategoryCode",
            "schema:codeValue": "environment:weather:rainwater:historical",
            "schema:name": "Environment — Weather — Rainwater Probability (Historical)"
          },
          "beckn:provider": {
            "beckn:id": "climate-data-provider-001",
            "beckn:descriptor": {
              "@type": "beckn:Descriptor",
              "schema:name": "ClimateData India Pvt. Ltd."
            }
          },
          "beckn:isActive": true,
          "beckn:rateable": true,
          "beckn:itemAttributes": {
            "@context": "https://raw.githubusercontent.com/beckn/DDM/main/specification/schema/DatasetItem/v1/context.jsonld",
            "@type": "DatasetItem",
            "schema:identifier": "ds-rainprob-delhi-ncr-march-2025",
            "schema:name": "Rainwater Probability — Delhi NCR — March 2025",
            "schema:description": "Daily precipitation probability (%) per 5km grid cell for Delhi-NCR, March 2025.",
            "schema:temporalCoverage": "2025-03-01/2025-03-31",
            "schema:spatialCoverage": {
              "@type": "schema:Place",
              "schema:name": "Delhi-NCR",
              "schema:description": "Coverage region for the dataset"
            },
            "schema:license": "https://creativecommons.org/licenses/by/4.0/",
            "schema:variableMeasured": [
              "PrecipitationProbability"
            ],
            "schema:measurementTechnique": "Model ensemble based on IMD and global forecast systems",
            "schema:usageInfo": "Intended for hydrology, agriculture planning, urban drainage capacity analysis, and research.",
            "schema:conditionsOfAccess": "Attribution required; no resale of raw data.",
            "schema:temporalResolution": "P1D",
            "schema:spatialResolution": {
              "schema:value": 5,
              "schema:unitText": "km"
            },
            "schema:creator": {
              "@type": "schema:Organization",
              "schema:name": "ClimateData India Pvt. Ltd.",
              "schema:url": "https://climate-data.example.com"
            },
            "schema:isBasedOn": [
              "IMD surface observations",
              "Global forecast system model outputs"
            ],
            "refreshType": "STATIC",
            "granularity": "GRID_DAILY",
            "rowCountEstimate": 31000,
            "columnCount": 5,
            "sensitivityLevel": "PUBLIC",
            "dataType": "GriddedProbabilityField",
            "rawUpdateFrequency": "PT1H",
            "latestRawDataAt": "2025-03-31T23:59:59Z",
            "qualityFlags": {
              "gapFilledPercent": 1.2,
              "outlierRemovedPercent": 0.5,
              "validationMethod": "IMD_RAIN_VALIDATION_2025"
            }
          }
        }
      ],
      "beckn:offers": [
        {
          "@context": "https://raw.githubusercontent.com/beckn/protocol-specifications-v2/core-v2.0.0-rc/schema/core/v2/context.jsonld",
          "@type": "beckn:Offer",
          "beckn:id": "offer-rainprob-delhi-2025-03-bulk-download",
          "beckn:descriptor": {
            "@type": "beckn:Descriptor",
            "schema:name": "One-Time Bulk Download — Rainwater Probability Delhi-NCR March 2025",
            "beckn:shortDesc": "Single download of the complete March 2025 rainwater probability dataset in Parquet format, valid for 7 days"
          },
          "beckn:provider": "climate-data-provider-001",
          "beckn:items": [
            "ds-rainprob-delhi-ncr-march-2025"
          ],
          "beckn:isActive": true,
          "beckn:validity": {
            "@type": "beckn:TimePeriod",
            "schema:startDate": "2025-02-01T00:00:00Z",
            "schema:endDate": "2026-01-31T23:59:59Z"
          },
          "beckn:price": {
            "currency": "INR",
            "value": 2499.00,
            "components": [
              {
                "type": "UNIT",
                "value": 2117.80,
                "currency": "INR",
                "description": "Rainwater Probability Delhi-NCR March 2025 — Parquet export"
              },
              {
                "type": "TAX",
                "value": 381.20,
                "currency": "INR",
                "description": "GST 18%"
              }
            ]
          }
        }
      ]
    }
  }
}

